maya_sdk/__init__.py
maya_sdk/api_client.py
maya_sdk/client.py
maya_sdk/errors.py
maya_sdk/version.py
maya_sdk-0.1.0.dist-info/LICENSE
maya_sdk-0.1.0.dist-info/METADATA
maya_sdk-0.1.0.dist-info/WHEEL
maya_sdk-0.1.0.dist-info/top_level.txt
maya_sdk-0.1.0.dist-info/RECORD
